async_kinesis-2.2.0.dist-info/licenses/LICENSE
kinesis/__init__.py
kinesis/aggregators.py
kinesis/base.py
kinesis/checkpointers.py
kinesis/consumer.py
kinesis/dynamodb.py
kinesis/exceptions.py
kinesis/metrics.py
kinesis/processors.py
kinesis/producer.py
kinesis/prometheus.py
kinesis/serializers.py
kinesis/timeout_compat.py
kinesis/utils.py
async_kinesis-2.2.0.dist-info/METADATA
async_kinesis-2.2.0.dist-info/WHEEL
async_kinesis-2.2.0.dist-info/top_level.txt
async_kinesis-2.2.0.dist-info/RECORD
