Metadata-Version: 2.4
Name: async-kinesis
Version: 2.2.0
Summary: AsyncIO Kinesis Library
Home-page: https://github.com/hampsterx/async-kinesis
Author: hampsterx
Author-email: tim.vdh@gmail.com
License: Apache2
Classifier: Development Status :: 4 - Beta
Classifier: Programming Language :: Python
Classifier: Programming Language :: Python :: 3
Classifier: Programming Language :: Python :: 3.9
Classifier: Programming Language :: Python :: 3.10
Classifier: Programming Language :: Python :: 3.11
Classifier: Programming Language :: Python :: 3.12
Classifier: Intended Audience :: Developers
Classifier: License :: OSI Approved :: Apache Software License
Requires-Python: >=3.9
License-File: LICENSE
Requires-Dist: aiobotocore>=1.3.3
Requires-Dist: async-timeout>=4.0.0
Requires-Dist: asyncio-throttle>=1.0.0
Provides-Extra: kpl
Requires-Dist: aws-kinesis-agg>=1.1.6; extra == "kpl"
Provides-Extra: redis
Requires-Dist: redis>=4.0.0; extra == "redis"
Provides-Extra: msgpack
Requires-Dist: msgpack>=0.6.1; extra == "msgpack"
Provides-Extra: prometheus
Requires-Dist: prometheus-client>=0.15.0; extra == "prometheus"
Provides-Extra: dynamodb
Requires-Dist: aioboto3>=11.0.0; extra == "dynamodb"
Dynamic: author
Dynamic: author-email
Dynamic: classifier
Dynamic: description
Dynamic: description-content-type
Dynamic: home-page
Dynamic: license
Dynamic: license-file
Dynamic: provides-extra
Dynamic: requires-dist
Dynamic: requires-python
Dynamic: summary
